Cryptorix/__init__.py
Cryptorix/aes.py
Cryptorix/exceptions.py
Cryptorix/fernet.py
Cryptorix/hybrid.py
Cryptorix/jwe.py
Cryptorix/kms.py
Cryptorix/secrets.py
cryptorix-1.1.0.dist-info/licenses/LICENSE
cryptorix-1.1.0.dist-info/METADATA
cryptorix-1.1.0.dist-info/WHEEL
cryptorix-1.1.0.dist-info/top_level.txt
cryptorix-1.1.0.dist-info/RECORD
