Metadata-Version: 2.4
Name: Cryptorix
Version: 1.1.0
Summary: A Python package that provides robust encryption and decryption mechanisms, utilizing AES, FERNET, JWE, Hybrid Encryption, AWS KMS, and AWS Secrets Manager.
Author-email: M Santhosh Kumar <santhoshse7en@gmail.com>
License-Expression: MIT
Project-URL: Documentation, https://github.com/santhoshse7en/cryptorix#readme
Project-URL: Source, https://github.com/santhoshse7en/cryptorix
Project-URL: Tracker, https://github.com/santhoshse7en/cryptorix/issues
Keywords: AES,FERNET,JWE,Hybrid Encryption,KMS,Secrets Manager,Encryption,Decryption,AWS,Security,Cryptography
Classifier: Programming Language :: Python :: 3
Classifier: Operating System :: OS Independent
Requires-Python: >=3.9
License-File: LICENSE
Requires-Dist: cryptography>=45.0.7
Requires-Dist: jwcrypto>=1.5.6
Requires-Dist: pycryptodome>=3.23.0
Requires-Dist: boto3>=1.40.23
Dynamic: license-file
